ml_pitch_models/__init__.py
ml_pitch_models/layers.py
ml_pitch_models/models.py
ml_pitch_models/pretrained.py
ml_pitch_models/stap.py
ml_pitch_models/utils.py
ml_pitch_models-0.0.2.dist-info/LICENSE
ml_pitch_models-0.0.2.dist-info/METADATA
ml_pitch_models-0.0.2.dist-info/WHEEL
ml_pitch_models-0.0.2.dist-info/top_level.txt
ml_pitch_models-0.0.2.dist-info/RECORD
